{
  "updated": "2026-06-26T00:45:24.697Z",
  "slots": {
    "home-top": {
      "enabled": false,
      "type": "image",
      "link": "",
      "alt": "",
      "image": ""
    },
    "home-feed": {
      "enabled": false,
      "type": "image",
      "link": "",
      "alt": "",
      "image": ""
    },
    "home-rail": {
      "enabled": true,
      "type": "image",
      "link": "",
      "alt": "",
      "image": "https://maxgazine.com/assets/uploads/1782434724703-ad-home-rail.png"
    },
    "home-footer": {
      "enabled": false,
      "type": "image",
      "link": "",
      "alt": "",
      "image": ""
    },
    "article-top": {
      "enabled": false,
      "type": "image",
      "link": "",
      "alt": "",
      "image": ""
    },
    "article-mid": {
      "enabled": false,
      "type": "image",
      "link": "",
      "alt": "",
      "image": ""
    },
    "article-end": {
      "enabled": false,
      "type": "image",
      "link": "",
      "alt": "",
      "image": ""
    },
    "coin-mid": {
      "enabled": false,
      "type": "image",
      "link": "",
      "alt": "",
      "image": ""
    },
    "coin-side": {
      "enabled": false,
      "type": "image",
      "link": "",
      "alt": "",
      "image": ""
    }
  },
  "popup": {
    "enabled": false,
    "type": "image",
    "link": "",
    "alt": "",
    "image": "",
    "frequencyHours": 24,
    "delaySeconds": 4
  }
}